pylibdsa/__init__.py
pylibdsa/algorithms.py
pylibdsa/structures.py
pylibdsa-0.4.0.dist-info/LICENSE
pylibdsa-0.4.0.dist-info/METADATA
pylibdsa-0.4.0.dist-info/WHEEL
pylibdsa-0.4.0.dist-info/top_level.txt
pylibdsa-0.4.0.dist-info/RECORD
