Metadata-Version: 2.1
Name: pylibdsa
Version: 0.4.0
Summary: A Python-based library for Data Structures and Algorithms
Home-page: https://github.com/cipherswami/pylibdsa
Author: Aravind Potluri
Author-email: aravindswami135@gmail.com
License: MIT
Keywords: Data Structures,Algorithms
Classifier: Programming Language :: Python :: 3
Classifier: License :: OSI Approved :: MIT License
Classifier: Operating System :: OS Independent
Requires-Python: >=3.6
License-File: LICENSE
Requires-Dist: numpy
